Workbook

Sheet Landed Cost
A1: LANDED COST CALCULATOR
A2: True per-unit cost of imported goods (China -> South Africa). Blue cells = your inputs.
A4: INPUTS (edit the blue cells)
A5: Units per shipment | B5: 1000
A6: Supplier unit cost (CNY / yuan) | B6: 20 | D6: From 1688 incl. China domestic freight + agent
A7: FX rate (ZAR per 1 CNY) | B7: 2.55 | D7: Use the rate you actually pay incl. bank spread
A8: International freight - total (ZAR) | B8: 12000 | D8: Sea = cheap/slow; air = fast/expensive
A9: Marine insurance (% of supplier+freight) | B9: 0.005 | D9: ~0.3-0.5% of CIF
A10: Customs duty rate (%) | B10: 0.2 | D10: VARIES BY HS CODE 0-45%+. CONFIRM with clearing agent
A11: Clearing & forwarding - total (ZAR) | B11: 2500 | D11: Agent fee, SAD500, port handling
A12: Inland transport port->warehouse (ZAR) | B12: 1500
A14: CALCULATION
A15: Supplier cost - total (ZAR) | B15: =B5*B6*B7 -> 51000
A16: International freight (ZAR) | B16: =B8 -> 12000
A17: Marine insurance (ZAR) | B17: =B9*(B15+B16) -> 315
A18: CIF / Customs Value (ZAR) | B18: =B15+B16+B17 -> 63315 | D18: Cost+Insurance+Freight
A19: Added Tax Value base (Customs +10%) | B19: =B18*1.1 -> 69646.5 | D19: +10% uplift: China is outside SACU
A20: Customs duty (ZAR) | B20: =B18*B10 -> 12663 | D20: Customs value x duty rate
A21: Import VAT 15% (ZAR) | B21: =(B19+B20)*0.15 -> 12346.425 | D21: (ATV + duty) x 15%
A22: Clearing & forwarding (ZAR) | B22: =B11 -> 2500
A23: Inland transport (ZAR) | B23: =B12 -> 1500
A24: TOTAL LANDED COST - shipment (ZAR) | B24: =B15+B16+B17+B20+B21+B22+B23 -> 92324.425
A25: LANDED COST PER UNIT (ZAR) | B25: =B24/B5 -> 92.324425 | D25: << use this as COGS
A28: NOTE: You are NOT VAT-registered, so the Import VAT (row 21) is a PERMANENT sunk cost in your COGS - you cannot claim it back.

Sheet Unit Economics
A1: UNIT ECONOMICS
A2: Per-order profitability. Target contribution margin > 35%.
A4: INPUTS
A5: Selling price per order (ZAR, incl) | B5: 249
A6: Landed cost per unit (ZAR) | B6: ='Landed Cost'!B25 -> 92.324425 | D6: Linked from Landed Cost sheet
A7: Delivery to customer per order (ZAR) | B7: 60 | D7: Courier last-mile
A8: PayFast fee - % of price | B8: 0.032 | D8: 3.2% card (PayFast 2026)
A9: PayFast fee - fixed per txn (ZAR) | B9: 2 | D9: + R2.00 per transaction
A10: Packaging per order (ZAR) | B10: 8
A11: Returns/refund allowance (% of price) | B11: 0.03
A12: CAC - ad cost per order (ZAR) | B12: 90 | D12: Customer acquisition cost
A14: CONTRIBUTION & BREAK-EVEN
A15: PayFast fee total (ZAR) | B15: =B5*B8+B9 -> 9.968
A16: Returns allowance (ZAR) | B16: =B5*B11 -> 7.47
A17: Total variable cost per order (ZAR) | B17: =B6+B7+B15+B10+B16 -> 177.76243 | D17: Landed+delivery+PayFast+packaging+returns
A18: Contribution margin per order (ZAR) | B18: =B5-B17 -> 71.237575 | D18: Before CAC
A19: Contribution margin % | B19: =B18/B5 -> 0.28609468 | D19: Target > 35%
A20: Break-even ROAS | B20: =1/B19 -> 3.4953464 | D20: Ad spend efficiency needed to break even
A21: Profit per order after CAC (ZAR) | B21: =B18-B12 -> -18.762425 | D21: True profit per sale
A22: Profit margin after CAC % | B22: =B21/B5 -> -0.075351104

Sheet Monthly P&L
A1: MONTHLY MANAGEMENT P&L
A2: Fill actuals each month. Reconcile to Xero + Nedbank + PayFast.
B4: Month 1 | C4: Month 2 | D4: Month 3
A5: Units sold | B5: 120 | C5: 0 | D5: 0
A6: Gross revenue (ZAR) | B6: 29880 | C6: 0 | D6: 0
A7: less: PayFast fees | B7: 1052 | C7: 0 | D7: 0
A8: Net revenue | B8: =B6-B7 -> 28828 | C8: =C6-C7 -> 0 | D8: =D6-D7 -> 0
A9: less: Landed COGS | B9: 12600 | C9: 0 | D9: 0
A10: GROSS PROFIT | B10: =B8-B9 -> 16228 | C10: =C8-C9 -> 0 | D10: =D8-D9 -> 0
A11: Gross margin % | B11: =IFERROR(B10/B6,0) -> 0.54310576 | C11: =IFERROR(C10/C6,0) -> 0 | D11: =IFERROR(D10/D6,0) -> 0
A12: less: Delivery (last-mile) | B12: 7200 | C12: 0 | D12: 0
A13: less: Packaging | B13: 960 | C13: 0 | D13: 0
A14: less: Ad spend (CAC) | B14: 10800 | C14: 0 | D14: 0
A15: less: Software (Xero etc.) | B15: 1095 | C15: 0 | D15: 0
A16: less: Other operating | B16: 0 | C16: 0 | D16: 0
A17: OPERATING PROFIT | B17: =B10-B12-B13-B14-B15-B16 -> -3827 | C17: =C10-C12-C13-C14-C15-C16 -> 0 | D17: =D10-D12-D13-D14-D15-D16 -> 0
A18: Operating margin % | B18: =IFERROR(B17/B6,0) -> -0.12807898 | C18: =IFERROR(C17/C6,0) -> 0 | D18: =IFERROR(D17/D6,0) -> 0

Sheet KPI Dashboard
A1: KPI DASHBOARD
A2: Key metrics to watch from day one.
B4: Value | C4: Target | D4: Notes
A5: Contribution margin % | B5: ='Unit Economics'!B19 -> 0.28609468 | C5: >35% | D5: Per order, before CAC
A6: Break-even ROAS | B6: ='Unit Economics'!B20 -> 3.4953464 | C6: <2.5x | D6: Lower is better
A7: Profit per order after CAC | B7: ='Unit Economics'!B21 -> -18.762425 | C7: >R0 | D7: Must be positive
A8: Landed cost per unit | B8: ='Landed Cost'!B25 -> 92.324425 | C8: - | D8: True COGS
A9: CAC payback (orders) | B9: 1 | C9: 1 order | D9: Single-purchase: pay back on order 1
A10: Days Inventory Outstanding | B10: 45 | C10: <60 | D10: Freight transit + holding time
A11: Cash-conversion cycle (days) | B11: =B10 -> 45 | C11: <60 | D11: DIO + DSO - DPO
A12: Cash runway (weeks) | B12: 8 | C12: >12 | D12: Weeks of cash at current burn
